iterable_serialization/__init__.py
iterable_serialization/serialization.py
iterable_serialization-0.0.1.dist-info/LICENSE
iterable_serialization-0.0.1.dist-info/METADATA
iterable_serialization-0.0.1.dist-info/WHEEL
iterable_serialization-0.0.1.dist-info/top_level.txt
iterable_serialization-0.0.1.dist-info/RECORD
