Metadata-Version: 2.1
Name: iterable-serialization
Version: 0.0.1
Summary: Serialization/deserialization of iterables of type 'str' to a single string.
Home-page: https://github.com/stefantaubert/iterable-serialization
Author: Stefan Taubert
Author-email: stefan.taubert@posteo.me
Maintainer: Stefan Taubert
Maintainer-email: stefan.taubert@posteo.me
License: MIT
Project-URL: Homepage, https://github.com/stefantaubert/iterable-serialization
Project-URL: Issues, https://github.com/stefantaubert/iterable-serialization/issues
Platform: UNKNOWN
Classifier: Development Status :: 2 - Pre-Alpha
Classifier: Operating System :: OS Independent
Classifier: Operating System :: MacOS
Classifier: Operating System :: POSIX
Classifier: Operating System :: POSIX :: BSD
Classifier: Operating System :: POSIX :: Linux
Classifier: Operating System :: Unix
Classifier: Operating System :: Microsoft :: Windows
Classifier: Programming Language :: Python
Classifier: Programming Language :: Python :: 3
Classifier: Programming Language :: Python :: 3.6
Classifier: Programming Language :: Python :: 3.7
Classifier: Programming Language :: Python :: 3.8
Classifier: Programming Language :: Python :: 3.9
Classifier: Programming Language :: Python :: 3.10
Classifier: License :: OSI Approved :: MIT License
Requires-Python: >=3.6
License-File: LICENSE
